turtleplus/__init__.py
turtleplus/draw.py
turtleplus/buttons/__init__.py
turtleplus/colors/__init__.py
turtleplus/key/__init__.py
turtleplus-0.1.dist-info/METADATA
turtleplus-0.1.dist-info/RECORD
turtleplus-0.1.dist-info/WHEEL
turtleplus-0.1.dist-info/top_level.txt
